kodi_remotecontrol/__init__.py
kodi_remotecontrol/eventclient.py
kodi_remotecontrol/gateway.py
kodi_remotecontrol-0.8.0.dist-info/LICENSE
kodi_remotecontrol-0.8.0.dist-info/METADATA
kodi_remotecontrol-0.8.0.dist-info/WHEEL
kodi_remotecontrol-0.8.0.dist-info/entry_points.txt
kodi_remotecontrol-0.8.0.dist-info/top_level.txt
kodi_remotecontrol-0.8.0.dist-info/RECORD
