Metadata-Version: 2.1
Name: kodi-remotecontrol
Version: 0.8.0
Summary: Python remote control gateway for Kodi server
Home-page: https://github.com/dmachard/kodi_remotecontrol
Author: Denis MACHARD
Author-email: d.machard@gmail.com
License: UNKNOWN
Keywords: kodi api remote control
Platform: any
Classifier: License :: OSI Approved :: MIT License
Classifier: Programming Language :: Python :: 3
Classifier: Operating System :: OS Independent
Classifier: Topic :: Software Development :: Libraries
Requires-Dist: websockets
Requires-Dist: requests
